code_black/__init__.py
code_black/code_black.py
code_black-0.1.0.dist-info/LICENSE
code_black-0.1.0.dist-info/METADATA
code_black-0.1.0.dist-info/WHEEL
code_black-0.1.0.dist-info/top_level.txt
code_black-0.1.0.dist-info/RECORD
