Metadata-Version: 2.1
Name: code-black
Version: 0.1.0
Summary: A package for randomly allocating patients to IC beds
Home-page: UNKNOWN
Author: Tim Schreuder
License: UNKNOWN
Platform: UNKNOWN
Requires-Python: >=3.0
